{
  "originUrl": "https://www.canon.ca",
  "aborted": false,
  "lastCrawled": "https://www.canon.ca/en/home",
  "urls": [
    {
      "url": "https://www.canon.ca/en/home",
      "source": "CRAWL",
      "targetPath": "/en/home",
      "id": "f33a64c343d5530b20d0a691f2ec907a25abf85f"
    },
    {
      "url": "https://www.canon.ca/fr/accueil",
      "source": "CRAWL",
      "targetPath": "/fr/accueil",
      "id": "d614014b9db96a78efb5bea66b1760f05e19e7d7"
    }
  ],
  "crawlOptions": {
    "timeout": 10000,
    "inclusionPatterns": [],
    "exclusionPatterns": [],
    "limit": 100,
    "sameDomain": true,
    "keepHash": false,
    "strategy": "crawl",
    "logger": {},
    "strategiesAttempted": [
      "SITEMAPS",
      "CRAWL"
    ]
  },
  "extractionErrors": [],
  "errorCountMessage": "none",
  "error": null
}